wagtail_donate-2.0.1.dist-info/licenses/LICENSE.txt
wagtaildonate/__init__.py
wagtaildonate/admin_forms.py
wagtaildonate/admin_urls.py
wagtaildonate/apps.py
wagtaildonate/blocks.py
wagtaildonate/configuration.py
wagtaildonate/constants.py
wagtaildonate/countries.py
wagtaildonate/exceptions.py
wagtaildonate/factories.py
wagtaildonate/settings.py
wagtaildonate/transaction_status.py
wagtaildonate/urls.py
wagtaildonate/views.py
wagtaildonate/address_lookups/__init__.py
wagtaildonate/address_lookups/base.py
wagtaildonate/address_lookups/generic.py
wagtaildonate/address_lookups/loqate.py
wagtaildonate/address_lookups/utils.py
wagtaildonate/admin_views/__init__.py
wagtaildonate/admin_views/export.py
wagtaildonate/api/__init__.py
wagtaildonate/api/metadata.py
wagtaildonate/api/urls.py
wagtaildonate/api/serializers/__init__.py
wagtaildonate/api/serializers/braintree.py
wagtaildonate/api/serializers/configuration.py
wagtaildonate/api/serializers/donations.py
wagtaildonate/api/serializers/gocardless.py
wagtaildonate/api/serializers/payment_method.py
wagtaildonate/api/serializers/recaptcha.py
wagtaildonate/api/serializers/utils.py
wagtaildonate/api/tests/__init__.py
wagtaildonate/api/tests/test_serializers.py
wagtaildonate/api/tests/test_utils.py
wagtaildonate/api/tests/test_views.py
wagtaildonate/api/views/__init__.py
wagtaildonate/api/views/configuration.py
wagtaildonate/api/views/donations.py
wagtaildonate/management/__init__.py
wagtaildonate/management/commands/__init__.py
wagtaildonate/management/commands/update_transaction_status.py
wagtaildonate/migrations/0001_initial.py
wagtaildonate/migrations/0002_add_fundraising_pay_in_fields.py
wagtaildonate/migrations/0003_donation.py
wagtaildonate/migrations/0004_thank_you_fields.py
wagtaildonate/migrations/0005_add_contact_details_fields.py
wagtaildonate/migrations/0006_donation_amount.py
wagtaildonate/migrations/0007_country.py
wagtaildonate/migrations/0008_donation_giftaid_organisation.py
wagtaildonate/migrations/0009_donation_memory.py
wagtail_donate-2.0.1.dist-info/METADATA
wagtail_donate-2.0.1.dist-info/WHEEL
wagtail_donate-2.0.1.dist-info/top_level.txt
wagtail_donate-2.0.1.dist-info/RECORD
